MANIFEST.in
requirements.txt
run_shmooze.sh
settings.json
setup.cfg
setup.py
supervisord.conf
bin/shmooze
bin/shmz
shmooze/__init__.py
shmooze/pool.py
shmooze/queue.py
shmooze/settings.py
shmooze.egg-info/PKG-INFO
shmooze.egg-info/SOURCES.txt
shmooze.egg-info/dependency_links.txt
shmooze.egg-info/not-zip-safe
shmooze.egg-info/requires.txt
shmooze.egg-info/top_level.txt
shmooze/lib/__init__.py
shmooze/lib/bot.py
shmooze/lib/cmdlog.py
shmooze/lib/database.py
shmooze/lib/packet.py
shmooze/lib/service.py
shmooze/modules/__init__.py
shmooze/modules/module.py
shmooze/modules/pymodule.py
shmooze/wsgi/__init__.py
shmooze/wsgi/__main__.py
shmooze/wsgi/endpoints.py
shmooze/wsgi/util.py
static/backbone.js
static/jquery.min.js
static/json2.js
static/shmooze.js
static/underscore.js
static/underscore.string.min.js