Metadata-Version: 1.1
Name: shmooze
Version: 1.2.1
Summary: Framework for processed-backed web applications
Home-page: https://github.com/zbanks/shmooze
Author: Zach Banks
Author-email: zbanks@mit.edu
License: UNKNOWN
Download-URL: https://github.com/zbanks/shmooze/tarball/1.2.1
Platform: UNKNOWN
